Workbook

Sheet Group
A1: Year | B1: Revenue_EURm | C1: Adjusted_EBITDA_EURm | D1: Operating_Profit_EURm | E1: Net_Profit_Parent_EURm | F1: SourceID | G1: Excel_Adj_Margin | H1: FX_USD_per_EUR | I1: Revenue_USDm | J1: Adjusted_EBITDA_USDm | K1: Operating_Profit_USDm | L1: Net_Profit_Parent_USDm
A2: 2022 | B2: 10340 | C2: 2135 | D2: 1600 | E2: 782 | F2: S1 | G2: =C2/B2 -> 0.20647969 | H2: 1.0534 | I2: =B2*H2 -> 10892.156 | J2: =C2*H2 -> 2249.009 | K2: =D2*H2 -> 1685.44 | L2: =E2*H2 -> 823.7588
A3: 2023 | B3: 11108 | C3: 2369 | D3: 1418 | E3: 1259 | F3: S1 | G3: =C3/B3 -> 0.21326972 | H3: 1.0817 | I3: =B3*H3 -> 12015.524 | J3: =C3*H3 -> 2562.5473 | K3: =D3*H3 -> 1533.8506 | L3: =E3*H3 -> 1361.8603
A4: 2024 | B4: 11834 | C4: 2661 | D4: 1775 | E4: 2086 | F4: S2 | G4: =C4/B4 -> 0.22486057 | H4: 1.082 | I4: =B4*H4 -> 12804.388 | J4: =C4*H4 -> 2879.202 | K4: =D4*H4 -> 1920.55 | L4: =E4*H4 -> 2257.052
A5: 2025 | B5: 12507 | C5: 2810 | D5: 1998 | E5: 1533 | F5: S2 | G5: =C5/B5 -> 0.22467418 | H5: 1.1306 | I5: =B5*H5 -> 14140.414 | J5: =C5*H5 -> 3176.986 | K5: =D5*H5 -> 2258.9388 | L5: =E5*H5 -> 1733.2098

Sheet Segments
A1: Year | B1: Segment | C1: Revenue_EURm | D1: Adjusted_EBITDA_EURm | E1: SourceID | F1: Excel_Adj_Margin | G1: FX_USD_per_EUR | H1: Revenue_USDm | I1: Adjusted_EBITDA_USDm
A2: 2022 | B2: Recorded Music | C2: 7937 | D2: 1900 | E2: S1 | F2: =D2/C2 -> 0.23938516 | G2: =_xlfn.XLOOKUP(A2,Group!$A$2:$A$5,Group!$H$2:$H$5) -> 1.0534 | H2: =C2*G2 -> 8360.8358 | I2: =D2*G2 -> 2001.46
A3: 2022 | B3: Music Publishing | C3: 1799 | D3: 410 | E3: S1 | F3: =D3/C3 -> 0.22790439 | G3: =_xlfn.XLOOKUP(A3,Group!$A$2:$A$5,Group!$H$2:$H$5) -> 1.0534 | H3: =C3*G3 -> 1895.0666 | I3: =D3*G3 -> 431.894
A4: 2022 | B4: Merchandising and Other | C4: 618 | D4: 36 | E4: S1 | F4: =D4/C4 -> 0.058252427 | G4: =_xlfn.XLOOKUP(A4,Group!$A$2:$A$5,Group!$H$2:$H$5) -> 1.0534 | H4: =C4*G4 -> 651.0012 | I4: =D4*G4 -> 37.9224
A5: 2023 | B5: Recorded Music | C5: 8461 | D5: 2042 | E5: S1 | F5: =D5/C5 -> 0.24134263 | G5: =_xlfn.XLOOKUP(A5,Group!$A$2:$A$5,Group!$H$2:$H$5) -> 1.0817 | H5: =C5*G5 -> 9152.2637 | I5: =D5*G5 -> 2208.8314
A6: 2023 | B6: Music Publishing | C6: 1956 | D6: 470 | E6: S1 | F6: =D6/C6 -> 0.2402863 | G6: =_xlfn.XLOOKUP(A6,Group!$A$2:$A$5,Group!$H$2:$H$5) -> 1.0817 | H6: =C6*G6 -> 2115.8052 | I6: =D6*G6 -> 508.399
A7: 2023 | B7: Merchandising and Other | C7: 706 | D7: 47 | E7: S1 | F7: =D7/C7 -> 0.066572238 | G7: =_xlfn.XLOOKUP(A7,Group!$A$2:$A$5,Group!$H$2:$H$5) -> 1.0817 | H7: =C7*G7 -> 763.6802 | I7: =D7*G7 -> 50.8399
A8: 2024 | B8: Recorded Music | C8: 8901 | D8: 2275 | E8: S2 | F8: =D8/C8 -> 0.25558926 | G8: =_xlfn.XLOOKUP(A8,Group!$A$2:$A$5,Group!$H$2:$H$5) -> 1.082 | H8: =C8*G8 -> 9630.882 | I8: =D8*G8 -> 2461.55
A9: 2024 | B9: Music Publishing | C9: 2121 | D9: 511 | E9: S2 | F9: =D9/C9 -> 0.24092409 | G9: =_xlfn.XLOOKUP(A9,Group!$A$2:$A$5,Group!$H$2:$H$5) -> 1.082 | H9: =C9*G9 -> 2294.922 | I9: =D9*G9 -> 552.902
A10: 2024 | B10: Merchandising and Other | C10: 842 | D10: 43 | E10: S2 | F10: =D10/C10 -> 0.051068884 | G10: =_xlfn.XLOOKUP(A10,Group!$A$2:$A$5,Group!$H$2:$H$5) -> 1.082 | H10: =C10*G10 -> 911.044 | I10: =D10*G10 -> 46.526
A11: 2025 | B11: Recorded Music | C11: 9456 | D11: 2423 | E11: S2 | F11: =D11/C11 -> 0.25623942 | G11: =_xlfn.XLOOKUP(A11,Group!$A$2:$A$5,Group!$H$2:$H$5) -> 1.1306 | H11: =C11*G11 -> 10690.954 | I11: =D11*G11 -> 2739.4438
A12: 2025 | B12: Music Publishing | C12: 2260 | D12: 549 | E12: S2 | F12: =D12/C12 -> 0.24292035 | G12: =_xlfn.XLOOKUP(A12,Group!$A$2:$A$5,Group!$H$2:$H$5) -> 1.1306 | H12: =C12*G12 -> 2555.156 | I12: =D12*G12 -> 620.6994
A13: 2025 | B13: Merchandising and Other | C13: 811 | D13: 16 | E13: S2 | F13: =D13/C13 -> 0.01972873 | G13: =_xlfn.XLOOKUP(A13,Group!$A$2:$A$5,Group!$H$2:$H$5) -> 1.1306 | H13: =C13*G13 -> 916.9166 | I13: =D13*G13 -> 18.0896

Sheet SOURCES
A1: SourceID | B1: Report | C1: Years Used | D1: URL
A2: S1 | B2: UMG FY2023 results PDF | C2: 2022-2023
A3: S2 | B3: UMG FY2025 results PDF | C3: 2024-2025
A4: S3 | B4: UMG 2025 Annual Report
